wgcna/__init__.py
wgcna/adjacency.py
wgcna/common.py
wgcna/connectivity.py
wgcna/trait.py
wgcna/wgcna.py
wgcna-0.4.0.dist-info/AUTHORS.rst
wgcna-0.4.0.dist-info/LICENSE
wgcna-0.4.0.dist-info/METADATA
wgcna-0.4.0.dist-info/WHEEL
wgcna-0.4.0.dist-info/top_level.txt
wgcna-0.4.0.dist-info/RECORD
