Metadata-Version: 2.1
Name: wgcna
Version: 0.4.0
Summary: WGCNA in Python. Fast.
Author-email: James Haberberger <jhaberbe@stanford.edu>
Maintainer-email: James Haberberger <jhaberbe@stanford.edu>
License: GNU General Public License v3
Project-URL: bugs, https://github.com/jhaberbe/wgcna/issues
Project-URL: changelog, https://github.com/jhaberbe/wgcna/blob/master/changelog.md
Project-URL: homepage, https://github.com/jhaberbe/wgcna
License-File: LICENSE
License-File: AUTHORS.rst
Requires-Dist: scanpy
Requires-Dist: scikit-learn
Requires-Dist: numpy
Requires-Dist: matplotlib
Requires-Dist: seaborn
Requires-Dist: scipy
Requires-Dist: anndata
Requires-Dist: dynamicTreeCut
Provides-Extra: dev
Requires-Dist: coverage ; extra == 'dev'
Requires-Dist: mypy ; extra == 'dev'
Requires-Dist: pytest ; extra == 'dev'
Requires-Dist: ruff ; extra == 'dev'
